re_gpt/__init__.py
re_gpt/async_chatgpt.py
re_gpt/errors.py
re_gpt/sync_chatgpt.py
re_gpt/utils.py
re_gpt-4.0.0.dist-info/LICENSE
re_gpt-4.0.0.dist-info/METADATA
re_gpt-4.0.0.dist-info/WHEEL
re_gpt-4.0.0.dist-info/top_level.txt
re_gpt-4.0.0.dist-info/RECORD
