Metadata-Version: 2.1
Name: re_gpt
Version: 4.0.0
Summary: Unofficial reverse-engineered ChatGPT API in Python.
Home-page: https://github.com/Zai-Kun/reverse-engineered-chatgpt
Author: Zai-Kun
Project-URL: Bug Tracker, https://github.com/Zai-Kun/reverse-engineered-chatgpt/issues
License-File: LICENSE
Requires-Dist: curl-cffi ==0.5.9
Requires-Dist: websockets ==12.0
